doodstream/__init__.py
doodstream/doodstream.py
doodstream-1.0.0.dist-info/LICENSE
doodstream-1.0.0.dist-info/METADATA
doodstream-1.0.0.dist-info/WHEEL
doodstream-1.0.0.dist-info/top_level.txt
doodstream-1.0.0.dist-info/RECORD
