Metadata-Version: 2.1
Name: doodstream
Version: 1.0.0
Summary: Unofficial python api wrapper from https://doodstream.com
Home-page: http://github.com/wahyubiman/DoodStream
Author: Wahyu Biman
Author-email: wahyubiman@gmail.com
Keywords: api,doodstream,video,hosting
Classifier: Development Status :: 3 - Alpha
Classifier: Programming Language :: Python :: 3
Classifier: Programming Language :: Python :: 3.8
License-File: LICENSE
Requires-Dist: requests
